sourcetypes/__init__.py
sourcetypes/py.typed
sourcetypes2-0.0.5.dist-info/LICENSE
sourcetypes2-0.0.5.dist-info/METADATA
sourcetypes2-0.0.5.dist-info/WHEEL
sourcetypes2-0.0.5.dist-info/top_level.txt
sourcetypes2-0.0.5.dist-info/RECORD
