Metadata-Version: 2.1
Name: sourcetypes2
Version: 0.0.5
Summary: Python Source Code Types For Inline Syntax Highlighting
Home-page: https://github.com/jurooravec/python-inline-source-2/tree/main/sourcetypes
Author: Juro Oravec
Classifier: Programming Language :: Python :: 3
Classifier: License :: OSI Approved :: MIT License
Classifier: Operating System :: OS Independent
Requires-Python: >=3.7
License-File: LICENSE
Requires-Dist: typing-extensions >=3.7.4
